downstream/__init__.py
downstream/__init__.pyi
downstream/__main__.py
downstream/_version.py
downstream/_auxlib/_ArgparseFormatter.py
downstream/_auxlib/__init__.py
downstream/_auxlib/_bit_floor.py
downstream/_auxlib/_bit_floor32.py
downstream/_auxlib/_bit_floor32_batched.py
downstream/_auxlib/_bit_floor_pl.py
downstream/_auxlib/_bitlen32.py
downstream/_auxlib/_bitlen32_batched.py
downstream/_auxlib/_bitlen32_scalar.py
downstream/_auxlib/_bitlen64.py
downstream/_auxlib/_bitlen_pl.py
downstream/_auxlib/_bitwise_count32_batched.py
downstream/_auxlib/_bitwise_count64_batched.py
downstream/_auxlib/_collect_chunked.py
downstream/_auxlib/_ctz.py
downstream/_auxlib/_ctz32.py
downstream/_auxlib/_ctz32_batched.py
downstream/_auxlib/_ctz32_scalar.py
downstream/_auxlib/_indexable_range.py
downstream/_auxlib/_interleave.py
downstream/_auxlib/_inverse_mod_n.py
downstream/_auxlib/_is_in_coverage_run.py
downstream/_auxlib/_is_in_unit_test.py
downstream/_auxlib/_jit.py
downstream/_auxlib/_jit_nb_or_np.py
downstream/_auxlib/_jit_prange.py
downstream/_auxlib/_modpow2.py
downstream/_auxlib/_modpow2_batched.py
downstream/_auxlib/_pack_hex.py
downstream/_auxlib/_pick_batched_chunk_size.py
downstream/_auxlib/_starstarmap.py
downstream/_auxlib/_unpack_hex.py
downstream/dataframe/__init__.py
downstream/dataframe/__init__.pyi
downstream/dataframe/_explode_lookup_packed.py
downstream/dataframe/_explode_lookup_unpacked.py
downstream/dataframe/_unpack_data_packed.py
downstream/dataframe/explode_lookup_packed_uint.py
downstream/dataframe/explode_lookup_unpacked_uint.py
downstream/dataframe/unpack_data_packed.py
downstream/dataframe/_impl/__init__.py
downstream/dataframe/_impl/_check_downstream_version.py
downstream/dataframe/_impl/_check_expected_columns.py
downstream/dstream/__init__.py
downstream/dstream/__init__.pyi
downstream/dstream/_hybrid_algo.py
downstream/dstream/_hybrid_algo_prefab.py
downstream/dstream/_primed_algo.py
downstream/dstream/_primed_algo_prefab.py
downstream-1.15.4.dist-info/LICENSE
downstream-1.15.4.dist-info/METADATA
downstream-1.15.4.dist-info/WHEEL
downstream-1.15.4.dist-info/top_level.txt
downstream-1.15.4.dist-info/RECORD
