Metadata-Version: 2.1
Name: downstream
Version: 1.15.4
Summary: downstream provides efficient, constant-space algorithms for stream curation
Author-email: Matthew Andres Moreno <m.more500@gmail.com>
License: MIT license
Project-URL: homepage, https://github.com/mmore500/downstream.git
Project-URL: repository, https://github.com/mmore500/downstream
Keywords: downstream
Classifier: Development Status :: 2 - Pre-Alpha
Classifier: Intended Audience :: Developers
Classifier: License :: OSI Approved :: MIT License
Classifier: Natural Language :: English
Classifier: Programming Language :: Python :: 3
Classifier: Programming Language :: Python :: 3.10
Classifier: Programming Language :: Python :: 3.11
Classifier: Programming Language :: Python :: 3.12
Requires-Python: >=3.10
License-File: LICENSE
Requires-Dist: lazy-loader>=0.4
Requires-Dist: joinem>=0.8.1
Requires-Dist: numpy>=2.0.0
Requires-Dist: opytional>=0.1.0
Requires-Dist: polars!=1.20.0,>=1.0.0
Provides-Extra: jit
Requires-Dist: numba>=0.60.0; extra == "jit"
Provides-Extra: release
Requires-Dist: bumpver==2022.1120; extra == "release"
Requires-Dist: twine==1.14.0; extra == "release"
Requires-Dist: wheel==0.45.0; extra == "release"
Requires-Dist: uv==0.2.34; extra == "release"
Requires-Dist: setuptools==75.5.0; extra == "release"
Provides-Extra: testing
Requires-Dist: black==22.10.0; extra == "testing"
Requires-Dist: isort==5.12.0; extra == "testing"
Requires-Dist: nbqa==1.9.0; extra == "testing"
Requires-Dist: pytest==8.3.3; extra == "testing"
Requires-Dist: pytest-xdist==3.2.1; extra == "testing"
Requires-Dist: ruff==0.0.260; extra == "testing"
Requires-Dist: tqdm==4.64.1; extra == "testing"
